[
    {
        "title": "auth",
        "endpoints": [
            {
                "isNew": true,
                "title": "Login with Username and Password",
                "description": "",
                "path": "/auth/login",
                "method": "POST",
                "contentType": "application/json",
                "requestBodyExample": {
                    "username": "string",
                    "password": "string"
                },
                "responseBodyExample": {
                    "accessToken": "user access token"
                },
                "requestHeadersExample": null
            },
            {
                "isNew": true,
                "title": "Profile",
                "description": "Get profile of the user",
                "path": "/auth/profile",
                "method": "GET",
                "contentType": "",
                "requestBodyExample": null,
                "responseBodyExample": {
                    "id": "User UUID",
                    "username": "abcxyz"
                },
                "requestHeadersExample": {
                    "Authorization": "Bearer <access token>"
                }
            }
        ]
    },
    {
        "title": "accounts",
        "endpoints": [
            {
                "isNew": true,
                "title": "Create Account",
                "description": "",
                "path": "/accounts/",
                "method": "POST",
                "contentType": "application/json",
                "requestBodyExample": {
                    "username": "string",
                    "password": "string"
                },
                "responseBodyExample": {
                    "id": "User UUID",
                    "username": "abcxyz"
                },
                "requestHeadersExample": null
            }
        ]
    }
]